automated_accessibility_testing/__init__.py
automated_accessibility_testing/accessibility_functions.py
automated_accessibility_testing/django.py
automated_accessibility_testing/exceptions.py
automated_accessibility_testing-1.0.1.dist-info/LICENSE
automated_accessibility_testing-1.0.1.dist-info/METADATA
automated_accessibility_testing-1.0.1.dist-info/WHEEL
automated_accessibility_testing-1.0.1.dist-info/top_level.txt
automated_accessibility_testing-1.0.1.dist-info/RECORD
