Metadata-Version: 2.1
Name: automated-accessibility-testing
Version: 1.0.1
Summary: package with the intention of automating accessibility tests for web development
Home-page: https://github.com/TCC2-Romeu/Pacote-Pip
Author: Romeu Carvalho Antunes
Author-email: romeu.antunes@outlook.com
License: UNKNOWN
Platform: UNKNOWN
Classifier: Programming Language :: Python :: 3
Classifier: License :: OSI Approved :: GNU General Public License v3 (GPLv3)
Classifier: Operating System :: OS Independent
Requires-Python: >=3.7
Requires-Dist: beautifulsoup4 (~=4.9)
Requires-Dist: joblib (~=0.17)
Requires-Dist: py-w3c (~=0.3)
Provides-Extra: django
Requires-Dist: django (~=2.2) ; extra == 'django'
